torch_subtract_membranes_2d/__init__.py
torch_subtract_membranes_2d/constants.py
torch_subtract_membranes_2d/membrane_model.py
torch_subtract_membranes_2d/model_membranes.py
torch_subtract_membranes_2d/refine_membrane.py
torch_subtract_membranes_2d/render_membranes.py
torch_subtract_membranes_2d/subtract_membranes.py
torch_subtract_membranes_2d/trace_paths.py
torch_subtract_membranes_2d/path_models/__init__.py
torch_subtract_membranes_2d/path_models/path_1d.py
torch_subtract_membranes_2d/path_models/path_2d.py
torch_subtract_membranes_2d/utils/__init__.py
torch_subtract_membranes_2d/utils/datetime_utils.py
torch_subtract_membranes_2d/utils/debug_utils.py
torch_subtract_membranes_2d/utils/image_utils.py
torch_subtract_membranes_2d/utils/path_utils.py
torch_subtract_membranes_2d/utils/plotting_utils.py
torch_subtract_membranes_2d/utils/serialization_utils.py
torch_subtract_membranes_2d/utils/skeleton_utils.py
torch_subtract_membranes_2d-0.0.6.dist-info/METADATA
torch_subtract_membranes_2d-0.0.6.dist-info/WHEEL
torch_subtract_membranes_2d-0.0.6.dist-info/licenses/LICENSE
torch_subtract_membranes_2d-0.0.6.dist-info/RECORD
